copyit/__init__.py
copyit-0.0.0.dist-info/LICENSE
copyit-0.0.0.dist-info/WHEEL
copyit-0.0.0.dist-info/METADATA
copyit-0.0.0.dist-info/RECORD
